cellshape/__init__.py
cellshape/main.py
cellshape/train.py
cellshape-0.0.31.dist-info/LICENSE
cellshape-0.0.31.dist-info/METADATA
cellshape-0.0.31.dist-info/WHEEL
cellshape-0.0.31.dist-info/entry_points.txt
cellshape-0.0.31.dist-info/top_level.txt
cellshape-0.0.31.dist-info/RECORD
