Metadata-Version: 2.1
Name: cellshape
Version: 0.0.31
Summary: 3D shape analysis using deep learning
Author: Matt De Vries, Lucas Dent, Adam Tyson
Author-email: mattdevries.ai@gmail.com
Project-URL: Source Code, https://github.com/Sentinal4D/cellshape
Project-URL: Bug Tracker, https://github.com/Sentinal4D/cellshape/issues
Classifier: Development Status :: 3 - Alpha
Classifier: Operating System :: POSIX :: Linux
Classifier: Operating System :: Microsoft :: Windows :: Windows 10
Classifier: Programming Language :: Python
Classifier: Programming Language :: Python :: 3.7
Classifier: Programming Language :: Python :: 3.8
Classifier: Programming Language :: Python :: 3.9
Classifier: Topic :: Scientific/Engineering :: Image Recognition
Classifier: Intended Audience :: Developers
Classifier: Intended Audience :: Science/Research
Requires-Python: >=3.7
License-File: LICENSE
Requires-Dist: torch
Requires-Dist: torchvision
Requires-Dist: pyntcloud
Requires-Dist: numpy
Requires-Dist: matplotlib
Requires-Dist: cellshape-helper
Requires-Dist: cellshape-cloud
Requires-Dist: cellshape-voxel
Requires-Dist: cellshape-cluster
Requires-Dist: umap-learn
Requires-Dist: scikit-learn
Requires-Dist: plotly
Requires-Dist: napari[all]
Provides-Extra: dev
Requires-Dist: black ; extra == 'dev'
Requires-Dist: black[jupyter] ; extra == 'dev'
Requires-Dist: pytest-cov ; extra == 'dev'
Requires-Dist: pytest ; extra == 'dev'
Requires-Dist: gitpython ; extra == 'dev'
Requires-Dist: coverage (>=5.0.3) ; extra == 'dev'
Requires-Dist: bump2version ; extra == 'dev'
Requires-Dist: pre-commit ; extra == 'dev'
Requires-Dist: flake8 ; extra == 'dev'
